nicpolpy/NICPolReduc.py
nicpolpy/__init__.py
nicpolpy/phot.py
nicpolpy/prepare.py
nicpolpy/preproc.py
nicpolpy/util.py
nicpolpy/ysfitsutilpy4nicpolpy/__init__.py
nicpolpy/ysfitsutilpy4nicpolpy/airmass.py
nicpolpy/ysfitsutilpy4nicpolpy/astroim.py
nicpolpy/ysfitsutilpy4nicpolpy/astrometry.py
nicpolpy/ysfitsutilpy4nicpolpy/combutil.py
nicpolpy/ysfitsutilpy4nicpolpy/filemgmt.py
nicpolpy/ysfitsutilpy4nicpolpy/fitting.py
nicpolpy/ysfitsutilpy4nicpolpy/hduutil.py
nicpolpy/ysfitsutilpy4nicpolpy/misc.py
nicpolpy/ysfitsutilpy4nicpolpy/preproc.py
nicpolpy/ysfitsutilpy4nicpolpy/imutil/__init__.py
nicpolpy/ysfitsutilpy4nicpolpy/imutil/docstrings.py
nicpolpy/ysfitsutilpy4nicpolpy/imutil/imarith.py
nicpolpy/ysfitsutilpy4nicpolpy/imutil/imcombine.py
nicpolpy/ysfitsutilpy4nicpolpy/imutil/imcopy.py
nicpolpy/ysfitsutilpy4nicpolpy/imutil/imsmooth.py
nicpolpy/ysfitsutilpy4nicpolpy/imutil/util_comb.py
nicpolpy/ysfitsutilpy4nicpolpy/imutil/util_lmedian.py
nicpolpy/ysfitsutilpy4nicpolpy/imutil/util_reject.py
nicpolpy/ysfitsutilpy4nicpolpy/tests/__init__.py
nicpolpy/ysfitsutilpy4nicpolpy/tests/test_misc.py
nicpolpy/ysphotutilpy4nicpolpy/__init__.py
nicpolpy/ysphotutilpy4nicpolpy/aperture.py
nicpolpy/ysphotutilpy4nicpolpy/apphot.py
nicpolpy/ysphotutilpy4nicpolpy/background.py
nicpolpy/ysphotutilpy4nicpolpy/center.py
nicpolpy/ysphotutilpy4nicpolpy/daopsf.py
nicpolpy/ysphotutilpy4nicpolpy/growth.py
nicpolpy/ysphotutilpy4nicpolpy/polarimetry.py
nicpolpy/ysphotutilpy4nicpolpy/queryutil.py
nicpolpy/ysphotutilpy4nicpolpy/seputil.py
nicpolpy/ysphotutilpy4nicpolpy/util.py
nicpolpy/ysphotutilpy4nicpolpy/tests/__init__.py
nicpolpy/ysphotutilpy4nicpolpy/tests/test_apphot.py
nicpolpy/ysphotutilpy4nicpolpy/tests/test_background.py
NICpolpy-0.1.5.dist-info/LICENSE
NICpolpy-0.1.5.dist-info/METADATA
NICpolpy-0.1.5.dist-info/WHEEL
NICpolpy-0.1.5.dist-info/top_level.txt
NICpolpy-0.1.5.dist-info/RECORD
