Metadata-Version: 2.1
Name: NICpolpy
Version: 0.1.5
Summary: Nishi-Harima Astronomical Observatory (NHAO) Near-Infrared Camera (NIC) polarimetry pipeline.
Home-page: https://github.com/ysBach/NICpolpy
Author: Yoonsoo P. Bach
Author-email: ysbach93@gmail.com,
License: BSD 3-clause
Project-URL: Source, https://github.com/ysBach/NICpolpy
Project-URL: Tracker, https://github.com/ysBach/NICpolpy/issues
Keywords: astronomy,polarimetry,near-infrared,data reduction,image analysis,Nishi-Harima Astronomical Observatory
Classifier: Development Status :: 5 - Production/Stable
Classifier: Environment :: Console
Classifier: Environment :: MacOS X
Classifier: Intended Audience :: Education
Classifier: Intended Audience :: Science/Research
Classifier: License :: OSI Approved :: BSD License
Classifier: Natural Language :: English
Classifier: Operating System :: OS Independent
Classifier: Programming Language :: Python :: 3.7
Classifier: Programming Language :: Python :: 3.8
Classifier: Programming Language :: Python :: 3.9
Classifier: Programming Language :: Python :: 3.10
Classifier: Topic :: Education
Classifier: Topic :: Scientific/Engineering :: Astronomy
Classifier: Topic :: Scientific/Engineering :: Image Processing
Requires-Python: >=3.7
License-File: LICENSE
Requires-Dist: numpy
Requires-Dist: scipy
Requires-Dist: bottleneck
Requires-Dist: astroscrappy
Requires-Dist: sep
Requires-Dist: astroquery
Requires-Dist: tqdm
Requires-Dist: pandas (>1.0)
Requires-Dist: astropy (>=5.0)
Requires-Dist: photutils (>=0.7)
Requires-Dist: ccdproc (>=1.3)
Requires-Dist: matplotlib (>=3)
